LICENSE
MANIFEST.in
README.md
setup.py
Topsis_Tushar_101803715.egg-info/PKG-INFO
Topsis_Tushar_101803715.egg-info/SOURCES.txt
Topsis_Tushar_101803715.egg-info/dependency_links.txt
Topsis_Tushar_101803715.egg-info/entry_points.txt
Topsis_Tushar_101803715.egg-info/requires.txt
Topsis_Tushar_101803715.egg-info/top_level.txt
Topsis_python/Topsis_101803715.py
Topsis_python/__init__.py