Metadata-Version: 2.1
Name: Topsis-Tushar-101803715
Version: 0.0.7
Summary: A Python package implementing TOPSIS technique.
Home-page: UNKNOWN
Author: Tushar Taneja
Author-email: ttaneja_be18@thapar.edu
License: MIT
Platform: UNKNOWN
Classifier: License :: OSI Approved :: MIT License
Classifier: Programming Language :: Python :: 3
Classifier: Programming Language :: Python :: 3.7
